bugzoo/.gitignore
bugzoo/__init__.py
bugzoo/cli/__init__.py
bugzoo/cli/app.py
bugzoo/cli/controllers/base.py
bugzoo/cli/controllers/bug.py
bugzoo/cli/controllers/container.py
bugzoo/cli/controllers/source.py
bugzoo/cli/controllers/tool.py
bugzoo/client/__init__.py
bugzoo/client/api.py
bugzoo/client/bug.py
bugzoo/client/container.py
bugzoo/client/dockerm.py
bugzoo/client/file.py
bugzoo/client/tools.py
bugzoo/cmd.py
bugzoo/compiler.py
bugzoo/core/__init__.py
bugzoo/core/bug.py
bugzoo/core/build.py
bugzoo/core/container.py
bugzoo/core/coverage.py
bugzoo/core/filechar.py
bugzoo/core/fileline.py
bugzoo/core/language.py
bugzoo/core/patch.py
bugzoo/core/source.py
bugzoo/core/spectra.py
bugzoo/core/test.py
bugzoo/core/tool.py
bugzoo/example
bugzoo/exceptions.py
bugzoo/manager.py
bugzoo/mgr/bug.py
bugzoo/mgr/build.py
bugzoo/mgr/container.py
bugzoo/mgr/coverage/__init__.py
bugzoo/mgr/coverage/extractor.py
bugzoo/mgr/coverage/gcov.py
bugzoo/mgr/file.py
bugzoo/mgr/source.py
bugzoo/mgr/tool.py
bugzoo/server/__init__.py
bugzoo/util.py
bugzoo/version.py
bugzoo-2.3.0.dist-info/LICENSE
bugzoo-2.3.0.dist-info/METADATA
bugzoo-2.3.0.dist-info/WHEEL
bugzoo-2.3.0.dist-info/entry_points.txt
bugzoo-2.3.0.dist-info/RECORD
