Metadata-Version: 2.1
Name: bugzoo
Version: 2.3.0
Summary: A platform for safely studying historical software versions.
Home-page: https://github.com/squaresLab/BugZoo
License: MIT
Author: Chris Timperley
Author-email: ctimperley@cmu.edu
Requires-Python: >=3.11,<4
Classifier: Intended Audience :: Developers
Classifier: License :: OSI Approved :: Apache Software License
Classifier: License :: OSI Approved :: MIT License
Classifier: Programming Language :: Python :: 3
Classifier: Programming Language :: Python :: 3.11
Classifier: Programming Language :: Python :: 3.12
Classifier: Programming Language :: Python :: 3.10
Classifier: Programming Language :: Python :: 3.9
Requires-Dist: GitPython (>=3.1.23)
Requires-Dist: attrs (>=19.3.0)
Requires-Dist: cement (>=3.0,<4.0)
Requires-Dist: chardet (>=3.0.4)
Requires-Dist: deprecated (>=1.2.6,<2.0.0)
Requires-Dist: docker (>=3.1.4)
Requires-Dist: dockerpty (>=0.4.1)
Requires-Dist: flask (>=2.2.5,<3.0.0)
Requires-Dist: psutil (>=5.0.0)
Requires-Dist: pyyaml (>=6.0.1)
Requires-Dist: tabulate (>=0.9.0)
Project-URL: Repository, https://github.com/squaresLab/BugZoo
